LICENSE
README.md
setup.py
pylavi/__init__.py
pylavi/assembler.py
pylavi/data_types.py
pylavi/file.py
pylavi/resource_types.py
pylavi/validate.py
pylavi.egg-info/PKG-INFO
pylavi.egg-info/SOURCES.txt
pylavi.egg-info/dependency_links.txt
pylavi.egg-info/entry_points.txt
pylavi.egg-info/requires.txt
pylavi.egg-info/top_level.txt