Metadata-Version: 2.1
Name: pylavi
Version: 0.3.2
Summary: Python LabVIEW File Parser
Home-page: https://github.com/marcpage/pylavi
Author: marcpage
Author-email: MarcAllenPage@gmail.com
License: Unlicense
Project-URL: Bug Reports, https://github.com/marcpage/pylavi/issues
Project-URL: Source, https://github.com/marcpage/pylavi/
Keywords: labview vi mnu ctl instruments parser extractor reverse-engineering development
Platform: UNKNOWN
Classifier: Development Status :: 1 - Planning
Classifier: Environment :: Console
Classifier: Intended Audience :: Developers
Classifier: Programming Language :: Python
Classifier: Programming Language :: Python :: 3
Classifier: License :: OSI Approved :: The Unlicense (Unlicense)
Classifier: Programming Language :: Python :: 3.9
Classifier: Topic :: Utilities
Classifier: Topic :: Software Development
License-File: LICENSE
